[
  {
    "@context": "http://www.w3.org/ns/anno.jsonld",
    "body": [
      {
        "purpose": "commenting",
        "type": "TextualBody",
        "value": "test updated"
      }
    ],
    "id": "https://visual-essays.app/jstor-labs--ve-content--sample--d6127469--8f292e3a",
    "seq": 0,
    "target": {
      "id": "https://visual-essays.app/jstor-labs/ve-content/sample/d6127469",
      "selector": {
        "conformsTo": "http://www.w3.org/TR/media-frags/",
        "type": "FragmentSelector",
        "value": "xywh=pixel:200.90908813476562,306.81817626953125,239.09091186523438,149.09091186523438"
      }
    },
    "type": "Annotation"
  }
]